setup.py
library_kostya/__init__.py
library_kostya/one.py
library_kostya/two.py
library_kostya.egg-info/PKG-INFO
library_kostya.egg-info/SOURCES.txt
library_kostya.egg-info/dependency_links.txt
library_kostya.egg-info/top_level.txt