Metadata-Version: 2.1
Name: library_kostya
Version: 0.0.1
Summary: My Package
Author: Kostya
Author-email: your@domain.com
